pjy.py
pjy-0.15.0.data/data/share/doc/pjy/README.rst
pjy-0.15.0.data/data/share/zsh/site-functions/_pjy
pjy-0.15.0.dist-info/METADATA
pjy-0.15.0.dist-info/WHEEL
pjy-0.15.0.dist-info/entry_points.txt
pjy-0.15.0.dist-info/licenses/COPYING.WTFPL
pjy-0.15.0.dist-info/RECORD
