Metadata-Version: 2.4
Name: pjy
Version: 0.15.0
Summary: pjy - command-line JSON processor
Project-URL: Project, https://gitlab.com/hydrargyrum/pjy
Author-email: Hg <dev@indigo.re>
License-Expression: WTFPL
License-File: COPYING.WTFPL
Keywords: filter,jq,json,processor,query
Classifier: Development Status :: 4 - Beta
Classifier: Environment :: Console
Classifier: Intended Audience :: Developers
Classifier: Intended Audience :: System Administrators
Classifier: License :: Public Domain
Classifier: Programming Language :: Python :: 3
Classifier: Programming Language :: Python :: 3 :: Only
Classifier: Programming Language :: Python :: 3.2
Classifier: Programming Language :: Python :: 3.3
Classifier: Programming Language :: Python :: 3.4
Classifier: Programming Language :: Python :: 3.5
Classifier: Programming Language :: Python :: 3.6
Classifier: Programming Language :: Python :: 3.7
Classifier: Programming Language :: Python :: 3.8
Classifier: Programming Language :: Python :: 3.9
Classifier: Programming Language :: Python :: 3.10
Classifier: Programming Language :: Python :: 3.11
Classifier: Topic :: Text Processing :: Filters
Classifier: Topic :: Utilities
Requires-Python: >=3
Provides-Extra: pygments
Requires-Dist: pygments; extra == 'pygments'
